django_gcloud_storage/__init__.py
django_gcloud_storage-0.5.0.dist-info/AUTHORS.rst
django_gcloud_storage-0.5.0.dist-info/LICENSE.txt
django_gcloud_storage-0.5.0.dist-info/METADATA
django_gcloud_storage-0.5.0.dist-info/WHEEL
django_gcloud_storage-0.5.0.dist-info/top_level.txt
django_gcloud_storage-0.5.0.dist-info/RECORD
