Metadata-Version: 2.1
Name: django-gcloud-storage
Version: 0.5.0
Summary: Django storage module implementation for Google Cloud Storage
Home-page: https://github.com/strayer/django-gcloud-storage
Author: Sven Grunewaldt
Author-email: strayer@olle-orks.org
License: BSD
Keywords: django-gcloud-storage gcloud google-cloud gcs
Platform: UNKNOWN
Classifier: Development Status :: 3 - Alpha
Classifier: Framework :: Django
Classifier: Framework :: Django :: 2.2
Classifier: Framework :: Django :: 3.2
Classifier: Framework :: Django :: 4.0
Classifier: Intended Audience :: Developers
Classifier: License :: OSI Approved :: BSD License
Classifier: Natural Language :: English
Classifier: Programming Language :: Python :: 3
Classifier: Programming Language :: Python :: 3.7
Classifier: Programming Language :: Python :: 3.8
Classifier: Programming Language :: Python :: 3.9
Classifier: Programming Language :: Python :: 3.10
License-File: LICENSE.txt
License-File: AUTHORS.rst
Requires-Dist: google-cloud-storage (>=1.10.0)
Requires-Dist: django (>=2.2)
